{
    "appid": "1140150",
    "type": "Game",
    "name": "东方光耀夜 ~ Lost Branch of Legend",
    "schinese_name": "东方光耀夜 ~ Lost Branch of Legend",
    "isfreeapp": "0",
    "change_number": "28997216",
    "update_time": "2025-05-15 15:52:14",
    "depot": {
        "hasdepotsindlc": "0",
        "1140151": {
            "config": {
                "oslist": "windows"
            },
            "manifests": {
                "public": {
                    "gid": "1250333962712791242",
                    "size": "4915619589",
                    "download": "1624886992"
                },
                "beta": {
                    "gid": "1250333962712791242",
                    "size": "4915619589",
                    "download": "1624886992"
                }
            },
            "decryptionkey": "50615b31d57243ccab3116b85ab46fe01d860584a3a8ede2bde1362d2d581cc1"
        },
        "1140152": {
            "config": {
                "oslist": "macos"
            },
            "manifests": {
                "public": {
                    "gid": "2118906820126742604",
                    "size": "4909482723",
                    "download": "1623886832"
                },
                "beta": {
                    "gid": "2118906820126742604",
                    "size": "4909482723",
                    "download": "1623886832"
                }
            },
            "decryptionkey": "c946bb7206279356b9b1a03620110ce4f354d253b4664f59f1f00da7e61b79ee"
        },
        "baselanguages": "",
        "branches": {
            "public": {
                "buildid": "18390541",
                "timeupdated": "1746717243"
            },
            "beta": {
                "buildid": "18390541",
                "description": "v1.7.2",
                "timeupdated": "1746716489"
            }
        },
        "privatebranches": "1"
    }
}