{
    "appid": "1161770",
    "type": "Game",
    "name": "Breeders of the Nephelym: Alpha",
    "schinese_name": "",
    "isfreeapp": "1",
    "change_number": "28984653",
    "update_time": "2025-05-14 23:59:59",
    "depot": {
        "228988": {
            "config": {
                "oslist": "windows"
            },
            "depotfromapp": "228980",
            "sharedinstall": "1"
        },
        "228990": {
            "config": {
                "oslist": "windows"
            },
            "depotfromapp": "228980",
            "sharedinstall": "1"
        },
        "1161771": {
            "config": {
                "oslist": "windows",
                "osarch": "64",
                "language": ""
            },
            "manifests": {
                "public": {
                    "gid": "7292788839526892796",
                    "size": "4550472897",
                    "download": "4434642720"
                }
            },
            "decryptionkey": "f721df393d668bd9b99270f51c5a715d40556fe826c5213700ed3b7e95858976"
        },
        "branches": {
            "public": {
                "buildid": "14141722",
                "timeupdated": "1713852655"
            }
        },
        "privatebranches": "1"
    }
}