{
    "appid": "1912420",
    "type": "Game",
    "name": "Sunshine Shuffle",
    "schinese_name": "",
    "isfreeapp": "0",
    "change_number": "28990907",
    "update_time": "2025-05-15 06:39:52",
    "depot": {
        "1912421": {
            "manifests": {
                "public": {
                    "gid": "2743942853976006432",
                    "size": "639184993",
                    "download": "215707552"
                }
            },
            "decryptionkey": "54c4ee065f071c0f2aae221213a5e7457f12752e8978304e133da65ed5178dc9"
        },
        "branches": {
            "public": {
                "buildid": "11651767",
                "timeupdated": "1688754289"
            }
        }
    }
}