{
    "appid": "1985420",
    "type": "Game",
    "name": "This is a Ghost",
    "schinese_name": "",
    "isfreeapp": "0",
    "change_number": "28995820",
    "update_time": "2025-05-15 14:10:06",
    "depot": {
        "228989": {
            "config": {
                "oslist": "windows"
            },
            "depotfromapp": "228980",
            "sharedinstall": "1"
        },
        "228990": {
            "config": {
                "oslist": "windows"
            },
            "depotfromapp": "228980",
            "sharedinstall": "1"
        },
        "1985421": {
            "config": {
                "oslist": "windows"
            },
            "manifests": {
                "public": {
                    "gid": "1916281716666879288",
                    "size": "6937874303",
                    "download": "6644192896"
                }
            },
            "decryptionkey": "05e05d6cee69333b9f22bdaead958c4f6cf1bcd850c7f96d2198326569848039"
        },
        "branches": {
            "public": {
                "buildid": "17783178",
                "timeupdated": "1742403082"
            }
        },
        "privatebranches": "1"
    }
}