{
    "appid": "2001070",
    "type": "Game",
    "name": "Heart of the Machine",
    "schinese_name": "人工智能的选择 Heart of the Machine",
    "isfreeapp": "0",
    "change_number": "28908758",
    "update_time": "2025-05-10 03:42:11",
    "depot": {
        "2001071": {
            "manifests": {
                "public": {
                    "gid": "3813764039248568534",
                    "size": "146524437",
                    "download": "79809888"
                },
                "older_but_stable": {
                    "gid": "386856967162268376",
                    "size": "145413427",
                    "download": "79225008"
                }
            },
            "decryptionkey": "1a1bb30e75dac9319e59c05cd2cf671bd58d69622641a320a63a2bd9665ce7a4"
        },
        "2001072": {
            "manifests": {
                "public": {
                    "gid": "5671723295650176079",
                    "size": "315547104",
                    "download": "81761104"
                },
                "older_but_stable": {
                    "gid": "6814715204784163009",
                    "size": "315542496",
                    "download": "81759600"
                }
            },
            "decryptionkey": "d99c074ccbebc30d9fd3c7e65ee1025c781f28985577c017a291b232cd65f927"
        },
        "2001073": {
            "config": {
                "oslist": "windows"
            },
            "manifests": {
                "public": {
                    "gid": "5097541098423699203",
                    "size": "3557822983",
                    "download": "1716349312"
                },
                "older_but_stable": {
                    "gid": "6751484518849162882",
                    "size": "3557791267",
                    "download": "1715997088"
                }
            },
            "decryptionkey": "dfdd7b00971120c31672747d712438f1195956496423bc46bf525178e8924d34"
        },
        "2001074": {
            "config": {
                "oslist": "macos"
            },
            "manifests": {
                "public": {
                    "gid": "8647310544186813526",
                    "size": "3753081823",
                    "download": "1743794672"
                },
                "older_but_stable": {
                    "gid": "4907296056156136717",
                    "size": "3753050107",
                    "download": "1743440032"
                }
            }
        },
        "branches": {
            "public": {
                "buildid": "18407921",
                "timeupdated": "1746819727"
            },
            "older_but_stable": {
                "buildid": "18078631",
                "description": "The most recent known-good build prior to the actual build",
                "timeupdated": "1746819703"
            }
        },
        "privatebranches": "1"
    }
}