{
    "appid": "2064650",
    "type": "Game",
    "name": "Tower of Fantasy",
    "schinese_name": "",
    "isfreeapp": "1",
    "change_number": "29034781",
    "update_time": "2025-05-17 08:21:55",
    "depot": {
        "228989": {
            "config": {
                "oslist": "windows"
            },
            "depotfromapp": "228980",
            "sharedinstall": "1"
        },
        "228990": {
            "config": {
                "oslist": "windows"
            },
            "depotfromapp": "228980",
            "sharedinstall": "1"
        },
        "2064651": {
            "manifests": {
                "public": {
                    "gid": "6538925693741770312",
                    "size": "90242355722",
                    "download": "84288469792"
                }
            },
            "decryptionkey": "9ec611ae31513d82d00a4290db1c1fea16a5c2df7f84ecc0adf89aa1792003e9"
        },
        "baselanguages": "english,german,french,thai,japanese,brazilian,latam",
        "hasdepotsindlc": "0",
        "branches": {
            "public": {
                "buildid": "18459794",
                "timeupdated": "1747292498"
            }
        },
        "privatebranches": "1"
    }
}