{
    "appid": "2158810",
    "type": "Game",
    "name": "Cosmic Coliseum",
    "schinese_name": "",
    "isfreeapp": "0",
    "change_number": "29046411",
    "update_time": "2025-05-18 13:58:38",
    "depot": {
        "2158811": {
            "manifests": {
                "public": {
                    "gid": "717205193097588564",
                    "size": "2672874656",
                    "download": "1004190672"
                }
            },
            "decryptionkey": "92841fb59aa8b7c0c44f750aa8c7d052bc11d76a32467c44a716efc4b774458b"
        },
        "branches": {
            "public": {
                "buildid": "18506163",
                "timeupdated": "1747533034"
            }
        },
        "privatebranches": "1"
    }
}