{
    "appid": "2218970",
    "type": "Game",
    "name": "Plains of Pain",
    "schinese_name": "",
    "isfreeapp": "0",
    "change_number": "29044199",
    "update_time": "2025-05-18 06:36:26",
    "depot": {
        "2218971": {
            "config": {
                "oslist": "windows",
                "osarch": "64"
            },
            "manifests": {
                "public": {
                    "gid": "2720853721710953579",
                    "size": "4213418166",
                    "download": "2073808880"
                },
                "previous": {
                    "gid": "7776901877103271621",
                    "size": "4213680177",
                    "download": "2073822176"
                },
                "v0.5": {
                    "gid": "7056385628732735879",
                    "size": "5409139794",
                    "download": "2707123312"
                }
            },
            "decryptionkey": "48988c75888be5d10947bc1742dc672de4fc08204c95d2d809398f3eb1def877"
        },
        "2218972": {
            "config": {
                "oslist": "windows",
                "osarch": "64"
            },
            "manifests": {
                "public": {
                    "gid": "1982847827617914424",
                    "size": "4213681745",
                    "download": "2074373712"
                }
            },
            "decryptionkey": ""
        },
        "branches": {
            "public": {
                "buildid": "18504319",
                "timeupdated": "1747507316"
            },
            "previous": {
                "buildid": "18502379",
                "description": "Previous working patch",
                "timeupdated": "1747507601"
            },
            "v0.5": {
                "buildid": "16964771",
                "description": "Plains of Pain v0.5",
                "timeupdated": "1744743012"
            }
        },
        "privatebranches": "1"
    }
}