{
    "appid": "2322340",
    "type": "Game",
    "name": "Monster High™ Skulltimate Secrets™",
    "schinese_name": "《Monster High™》之骷髅终极秘密™",
    "isfreeapp": "0",
    "change_number": "29010787",
    "update_time": "2025-05-16 04:13:03",
    "depot": {
        "2322341": {
            "manifests": {
                "public": {
                    "gid": "8613820635070448946",
                    "size": "2959703383",
                    "download": "2283666080"
                }
            },
            "decryptionkey": "1a1e762a01827a8eaaeb05f6b453febda5159a3b158c824c41bf9d59bf721fb0"
        },
        "branches": {
            "public": {
                "buildid": "15593201",
                "timeupdated": "1725509099"
            }
        },
        "privatebranches": "1"
    }
}