{
    "appid": "2374320",
    "type": "Game",
    "name": "Heroes Of  Loot: Gauntlet Of Power",
    "schinese_name": "寻宝英雄：力量手套 Heroes Of Loot: Gauntlet Of Power",
    "isfreeapp": "0",
    "change_number": "29011300",
    "update_time": "2025-05-16 04:48:46",
    "depot": {
        "2374321": {
            "config": {
                "oslist": "windows"
            },
            "manifests": {
                "public": {
                    "gid": "643245537054557592",
                    "size": "115720043",
                    "download": "92157424"
                }
            },
            "decryptionkey": "a098ac88d513bd5d63c36ea8262326b981c687dd6549aa0cd4e021e9f9ea7ac0"
        },
        "2374322": {
            "config": {
                "oslist": "linux"
            },
            "manifests": {
                "public": {
                    "gid": "8135557961138258905",
                    "size": "125164118",
                    "download": "94550688"
                }
            }
        },
        "2374323": {
            "config": {
                "oslist": "macos",
                "osarch": "64"
            },
            "manifests": {
                "public": {
                    "gid": "6749729062856403603",
                    "size": "127903859",
                    "download": "94642848"
                }
            }
        },
        "branches": {
            "public": {
                "buildid": "17076047",
                "timeupdated": "1737454727"
            }
        }
    }
}