{
    "appid": "2823160",
    "type": "Game",
    "name": "Gung Beetle",
    "schinese_name": "枪螂",
    "isfreeapp": "0",
    "change_number": "29047596",
    "update_time": "2025-05-18 17:41:56",
    "depot": {
        "baselanguages": "english",
        "2823161": {
            "manifests": {
                "public": {
                    "gid": "2165218192119531868",
                    "size": "594033923",
                    "download": "102055536"
                }
            },
            "decryptionkey": "cadb468e2f214f4ee360c905d8ee0e282706b6be4e4a4da670d613a4bf8cd030"
        },
        "2823163": {},
        "branches": {
            "public": {
                "buildid": "18507798",
                "timeupdated": "1747561313"
            }
        },
        "privatebranches": "1"
    }
}