{
    "appid": "670160",
    "type": "Game",
    "name": "D'LIRIUM",
    "schinese_name": "",
    "isfreeapp": "0",
    "change_number": "28911874",
    "update_time": "2025-05-10 08:02:54",
    "depot": {
        "baselanguages": "english,german,french,schinese,tchinese,russian,polish,hungarian,czech,ukrainian",
        "hasdepotsindlc": "1",
        "workshopdepot": "670160",
        "670161": {
            "config": {
                "oslist": "windows",
                "language": ""
            },
            "manifests": {
                "public": {
                    "gid": "5739531772510468607",
                    "size": "538508623",
                    "download": "239813792"
                },
                "vm_stable": {
                    "gid": "1069171029527562269",
                    "size": "515547611",
                    "download": "236201344"
                }
            },
            "decryptionkey": "2772a1ea6667775a9bcbdfb20c5c8a6eea1aa04aeb3b4e8056e8b574515fa0d7"
        },
        "branches": {
            "public": {
                "buildid": "18410171",
                "timeupdated": "1746835370"
            },
            "vm_stable": {
                "buildid": "18409980",
                "description": "More demanding on hardware, but verbose error output.",
                "timeupdated": "1746833629"
            }
        },
        "workshopdepotdecryptionkey": "9831eb16e16ae9d24fa70566adc11e1f61b532e1706540a26d21442a992a282c"
    }
}